micron/__init__.py
micron/builder.py
micron/colors.py
micron_builder-0.1.3.dist-info/licenses/LICENSE
micron_builder-0.1.3.dist-info/METADATA
micron_builder-0.1.3.dist-info/WHEEL
micron_builder-0.1.3.dist-info/top_level.txt
micron_builder-0.1.3.dist-info/RECORD
