Metadata-Version: 2.4
Name: micron-builder
Version: 0.1.3
Summary: Fluent string builder for micron markup
Author-email: Thomas La Mendola <thomas.lamendola@gmail.com>
License: MIT
Keywords: micron,builder,colors,ansi,terminal
Classifier: Development Status :: 3 - Alpha
Classifier: Intended Audience :: Developers
Classifier: License :: OSI Approved :: MIT License
Classifier: Programming Language :: Python :: 3
Classifier: Programming Language :: Python :: 3 :: Only
Classifier: Programming Language :: Python :: 3.10
Classifier: Programming Language :: Python :: 3.11
Classifier: Programming Language :: Python :: 3.12
Requires-Python: >=3.10
License-File: LICENSE
Dynamic: license-file
